{
    "FirmwareVersions": [
        {
            "FirmwareName": "Alpha Version 1.0.0.0",
            "DownloadUrl": "/systemfirmware/firmware.bin",
            "FirmwareType": 4,
            "SystemType": 1,
            "VersionNumber": "1.0.0.0"
        },
        {
            "FirmwareName": "Alpha Version 1.0.0.1",
            "DownloadUrl": "/systemfirmware/firmware.bin",
            "FirmwareType": 4,
            "SystemType": 1,
            "VersionNumber": "1.0.0.1"
        },
        {
            "FirmwareName": "Alpha Version 1.0.0.4",
            "DownloadUrl": "/systemfirmware/firmware.bin",
            "FirmwareType": 4,
            "SystemType": 1,
            "VersionNumber": "1.0.0.4"
        },
        {
            "FirmwareName": "Alpha Version 1.0.0.5",
            "DownloadUrl": "/systemfirmware/firmware.bin",
            "FirmwareType": 4,
            "SystemType": 1,
            "VersionNumber": "1.0.0.5"
        }
    ]
}